0318/decoder_3_8.v
module decoder(E , In , Out);
    input E;                                        //致能輸入
    input [2:0] In;                                 //三位元輸入
    output [7:0] Out;                               //八位元輸出
    wire E1 , G1 , G2;                              //內部線路
not u1(E1 , In[2]);                                 //將In[2]之值not傳入E1
and a1(G1 , E , In[2]);                             //將E以及In[2] AND 傳入G1
and a2(G2 , E , E1);                                //將E以及E1 AND 傳入G2
decoder_2_4 block1(G1 , In[1 : 0] , Out[7 : 4]);    //將In傳入decoder_2_4模組並取得Out輸出
decoder_2_4 block2(G2 , In[1 : 0] , Out[3 : 0]);    //將In傳入decoder_2_4模組並取得Out輸出
endmodule

module decoder_2_4(E , In , Out);
    input E;                        //致能輸入
    input [1:0] In;                 //三位元輸入
    output [3:0] Out;               //八位元輸出
    wire [3:0] Out;                 //內部線路
assign Out = E ? 4'b1 << In : 4'h0; //若有致能輸入，將"0001"依照輸入In之值左移。若無，則輸出"0000"。
endmodule

// module decoder(E , In , Out);
// input E;                                //致能輸入
// input [2:0] In;                         //三位元輸入
// output [7:0] Out;                       //八位元輸出
// wire [7:0] Out;                         //排線
// assign Out = E ? (8'b1 << In) : 8'h0;   //若有致能輸入，將"00000001"依照輸入In之值左移。若無，則輸出"00000000"。
// endmodule

0318/decoder_3_8_tb.v
module decoder_3_8_tb;
    reg E_tb;           //智能輸入暫存
    reg [2:0] In_tb;    //輸入暫存
    wire [7:0] Out_tb;  //輸出暫存
    decoder decoder_1(.E(E_tb), .In(In_tb), .Out(Out_tb));  //將輸入傳入decoder模組並取得輸出
initial begin
    #0 E_tb = 0; In_tb = 3'b000;    //模擬輸入  致能關閉
    #10 E_tb = 1; In_tb = 3'b000;   //模擬輸入  二進位數字000
    #10 E_tb = 1; In_tb = 3'b001;   //模擬輸入  二進位數字001
    #10 E_tb = 1; In_tb = 3'b010;   //模擬輸入  二進位數字010
    #10 E_tb = 1; In_tb = 3'b011;   //模擬輸入  二進位數字011
    #10 E_tb = 1; In_tb = 3'b100;   //模擬輸入  二進位數字100
    #10 E_tb = 1; In_tb = 3'b101;   //模擬輸入  二進位數字101
    #10 E_tb = 1; In_tb = 3'b110;   //模擬輸入  二進位數字110
    #10 E_tb = 1; In_tb = 3'b111;   //模擬輸入  二進位數字111
    #10 $finish;
end
initial begin
    $dumpfile("decoder_3_8.vcd");   //欲存入之檔案
    $dumpvars(0, decoder_1);    //將所有變數存入
end
endmodule

0318/decoder_3_8.vcd
$date
	Fri Mar 25 13:26:30 2022
$end
$version
	Icarus Verilog
$end
$timescale
	1s
$end
$scope module decoder_3_8_tb $end
$scope module decoder_1 $end
$var wire 1 ! E $end
$var wire 1 " E1 $end
$var wire 1 # G1 $end
$var wire 1 $ G2 $end
$var wire 3 % In [2:0] $end
$var wire 8 & Out [7:0] $end
$scope module block1 $end
$var wire 1 # E $end
$var wire 2 ' In [1:0] $end
$var wire 4 ( Out [3:0] $end
$upscope $end
$scope module block2 $end
$var wire 1 $ E $end
$var wire 2 ) In [1:0] $end
$var wire 4 * Out [3:0] $end
$upscope $end
$upscope $end
$upscope $end
$enddefinitions $end
#0
$dumpvars
b0 *
b0 )
b0 (
b0 '
b0 &
b0 %
0$
0#
1"
0!
$end
#10
b1 &
b1 *
1$
1!
#20
b10 &
b10 *
b1 '
b1 )
b1 %
#30
b100 &
b100 *
b10 '
b10 )
b10 %
#40
b1000 &
b1000 *
b11 '
b11 )
b11 %
#50
0$
b1 (
0"
1#
b10000 &
b0 *
b0 '
b0 )
b100 %
#60
b100000 &
b10 (
b1 '
b1 )
b101 %
#70
b1000000 &
b100 (
b10 '
b10 )
b110 %
#80
b10000000 &
b1000 (
b11 '
b11 )
b111 %
