0318/decoder_3_8.v
module decoder(E , In , Out);
input E;
input [2:0] In;
output [7:0] Out;
wire [7:0] Out;
assign Out = E ? (8'b1 << In) : 8'h0;
endmodule
// module decoder_3_8(E , In , Out);
//     input E; 
//     input [2:0] In;
//     output [7:0] Out; 
//     wire E1 , G1 , G2;
//     not u1(E1 , In[2]); 
//     and a1(G1 , E , In[2]);
//     and a2(G2 , E , E1);
//     decoder_2_4 block1(G1 , In[1 : 0] , Out[7 : 4]);
//     decoder_2_4 block2(G2 , In[1 : 0] , Out[3 : 0]);
// endmodule

// module decoder(E , In , Out);
// input E;
// input [2:0] In;
// output [7:0] Out;
// wire [7:0] Out;
// assign Out = E ? (8'b1 << In) : 8'h0;
// endmodule

// module decoder_2_4(E , In , Out);
// input E; 
// input [1:0] In;
// output [3:0]Out; 
// wire [3:0] Out;
// assign Out = E ? 1'b1 << In : 4'h0;
// endmodule

// module clkgen(clka, clkb, clka_out, clkb_out);
// input clka, clkb;
// output clka_out, clkb_out;
// reg clka_out, clkb_out;
//     always @(clka) begin 
//         clka_out = clka;
//     end
//     always @(clkb) begin
//         clkb_out = clkb;
//     end
// endmodule

0318/decoder_3_8_tb.v
module decoder_3_8_tb;
    reg E_tb;
    reg [2:0] In_tb;
    wire [7:0] Out_tb;
    decoder decoder_1(.E(E_tb), .In(In_tb), .Out(Out_tb));
initial begin
    #0 E_tb = 0; In_tb = 3'b000;
    #10 E_tb = 1; In_tb = 3'b000;
    #10 E_tb = 1; In_tb = 3'b001;
    #10 E_tb = 1; In_tb = 3'b010;
    #10 E_tb = 1; In_tb = 3'b011;
    #10 E_tb = 1; In_tb = 3'b100;
    #10 E_tb = 1; In_tb = 3'b101;
    #10 E_tb = 1; In_tb = 3'b110;
    #10 E_tb = 1; In_tb = 3'b111;
    #10 $finish;
end
initial begin
    $dumpfile("decoder.vcd");
    $dumpvars(0, decoder_1);
end
endmodule
// module decoder_3_8_tb;
//     reg E_tb;
//     reg clka, clkb;
//     reg [2:0] In_tb;
//     wire [7:0] Out_tb;
//     wire clka_out, clkb_out;
//     decoder decoder_1(.E(E_tb), .In(In_tb), .Out(Out_tb));
//     clkgen clkgen_1(.clka(clka), .clkb(clkb), .clka_out(clka_out), .clkb_out(clkb_out));
//     initial begin
//         clka = 1'b0; clkb = 1'b0;
//     end
//     always begin 
//         #10 clka = ~clka; 
//     end
//     always begin
//         #20 clkb = ~clkb;
// end
// initial begin
//     #0 E_tb = 0; In_tb = 3'b000;
//     #10 E_tb = 1; In_tb = 3'b000;
//     #10 E_tb = 1; In_tb = 3'b001;
//     #10 E_tb = 1; In_tb = 3'b010;
//     #10 E_tb = 1; In_tb = 3'b011;
//     #10 E_tb = 1; In_tb = 3'b100;
//     #10 E_tb = 1; In_tb = 3'b101;
//     #10 E_tb = 1; In_tb = 3'b110;
//     #10 E_tb = 1; In_tb = 3'b111;
//     #10 $finish;
// end
// initial begin
//     $dumpfile("decoder.vcd");
//     $dumpvars(0, decoder_1);
//     $dumpvars(0, clkgen_1);
// end
// endmodule

0318/decoder.vcd
$date
	Fri Mar 18 16:06:55 2022
$end
$version
	Icarus Verilog
$end
$timescale
	1s
$end
$scope module decoder_3_8_tb $end
$scope module decoder_1 $end
$var wire 1 ! E $end
$var wire 3 " In [2:0] $end
$var wire 8 # Out [7:0] $end
$upscope $end
$upscope $end
$enddefinitions $end
#0
$dumpvars
b0 #
b0 "
0!
$end
#10
b1 #
1!
#20
b10 #
b1 "
#30
b100 #
b10 "
#40
b1000 #
b11 "
#50
b10000 #
b100 "
#60
b100000 #
b101 "
#70
b1000000 #
b110 "
#80
b10000000 #
b111 "
